 [
        {
            "CODE": "M-00001",
            "NAME": "SİNGLE ESPRESSO",
            "BUYINGPRICE": "0",
            "PRICE": "12",
            "CURRENCY": "TRY",
            "TYPE": "SICAK KAHVE",
            "TAX": "0",
            "UNIT": "ADED",
            "DISCOUNT": "0"
        },
        {
            "CODE": "M-00002",
            "NAME": "DOUBLE ESPRESSO",
            "BUYINGPRICE": "0",
            "PRICE": "23",
            "CURRENCY": "TRY",
            "TYPE": "SICAK KAHVE",
            "TAX": "0",
            "UNIT": "ADED",
            "DISCOUNT": "0"
        },
        {
            "CODE": "M-00003",
            "NAME": "CORTADO",
            "BUYINGPRICE": "0",
            "PRICE": "4",
            "CURRENCY": "TRY",
            "TYPE": "SICAK KAHVE",
            "TAX": "0",
            "UNIT": "ADED",
            "DISCOUNT": "0"
        },
        {
            "CODE": "M-00004",
            "NAME": "ESPRESSO MACCHİATO",
            "BUYINGPRICE": "0",
            "PRICE": "6",
            "CURRENCY": "TRY",
            "TYPE": "SICAK KAHVE",
            "TAX": "0",
            "UNIT": "ADED",
            "DISCOUNT": "0"
        },
        {
            "CODE": "M-00005",
            "NAME": "AMERİCANO",
            "BUYINGPRICE": "0",
            "PRICE": "8",
            "CURRENCY": "TRY",
            "TYPE": "SICAK KAHVE",
            "TAX": "0",
            "UNIT": "ADED",
            "DISCOUNT": "0"
        },
        {
            "CODE": "M-00006",
            "NAME": "ORTA AMERİCANO",
            "BUYINGPRICE": "0",
            "PRICE": "23",
            "CURRENCY": "TRY",
            "TYPE": "SICAK KAHVE",
            "TAX": "0",
            "UNIT": "ADED",
            "DISCOUNT": "0"
        },
        {
            "CODE": "M-00007",
            "NAME": "RED EYE",
            "BUYINGPRICE": "0",
            "PRICE": "12",
            "CURRENCY": "TRY",
            "TYPE": "SICAK KAHVE",
            "TAX": "0",
            "UNIT": "ADED",
            "DISCOUNT": "0"
        },
        {
            "CODE": "M-00008",
            "NAME": "FLAT WHİTE",
            "BUYINGPRICE": "0",
            "PRICE": "32",
            "CURRENCY": "TRY",
            "TYPE": "SICAK KAHVE",
            "TAX": "0",
            "UNIT": "ADED",
            "DISCOUNT": "0"
        },
        {
            "CODE": "M-00009",
            "NAME": "LATTE",
            "BUYINGPRICE": "0",
            "PRICE": "4",
            "CURRENCY": "TRY",
            "TYPE": "SICAK KAHVE",
            "TAX": "0",
            "UNIT": "ADED",
            "DISCOUNT": "0"
        },
        {
            "CODE": "M-00010",
            "NAME": "MOCHA",
            "BUYINGPRICE": "0",
            "PRICE": "4",
            "CURRENCY": "TRY",
            "TYPE": "SICAK KAHVE",
            "TAX": "0",
            "UNIT": "ADED",
            "DISCOUNT": "0"
        },
        {
            "CODE": "M-00011",
            "NAME": "ROOİBOS CORTADO",
            "BUYINGPRICE": "0",
            "PRICE": "12",
            "CURRENCY": "TRY",
            "TYPE": "SICAK KAHVE",
            "TAX": "0",
            "UNIT": "ADED",
            "DISCOUNT": "0"
        },
        {
            "CODE": "M-00012",
            "NAME": "SICAK ÇİKOLATA",
            "BUYINGPRICE": "0",
            "PRICE": "11",
            "CURRENCY": "TRY",
            "TYPE": "SICAK KAHVE",
            "TAX": "0",
            "UNIT": "ADED",
            "DISCOUNT": "0"
        },
        {
            "CODE": "M-00013",
            "NAME": "CHAİ TEA LATTE",
            "BUYINGPRICE": "0",
            "PRICE": "12",
            "CURRENCY": "TRY",
            "TYPE": "SICAK KAHVE",
            "TAX": "0",
            "UNIT": "ADED",
            "DISCOUNT": "0"
        },
        {
            "CODE": "M-00014",
            "NAME": "İCED LATTE",
            "BUYINGPRICE": "0",
            "PRICE": "23",
            "CURRENCY": "TRY",
            "TYPE": "SOĞUK KAHVELER",
            "TAX": "0",
            "UNIT": "ADED",
            "DISCOUNT": "0"
        },
        {
            "CODE": "M-00015",
            "NAME": "İCED AMERİCANO",
            "BUYINGPRICE": "0",
            "PRICE": "12",
            "CURRENCY": "TRY",
            "TYPE": "SOĞUK KAHVELER",
            "TAX": "0",
            "UNIT": "ADED",
            "DISCOUNT": "0"
        },
        {
            "CODE": "M-00016",
            "NAME": "İCED MOCHA",
            "BUYINGPRICE": "0",
            "PRICE": "12",
            "CURRENCY": "TRY",
            "TYPE": "SOĞUK KAHVELER",
            "TAX": "0",
            "UNIT": "ADED",
            "DISCOUNT": "0"
        },
        {
            "CODE": "M-00017",
            "NAME": "İCED CHAİ TEA LATTE",
            "BUYINGPRICE": "0",
            "PRICE": "12",
            "CURRENCY": "TRY",
            "TYPE": "SOĞUK KAHVELER",
            "TAX": "0",
            "UNIT": "ADED",
            "DISCOUNT": "0"
        },
        {
            "CODE": "M-00018",
            "NAME": "JAPANESE CLOD DRİP",
            "BUYINGPRICE": "0",
            "PRICE": "12",
            "CURRENCY": "TRY",
            "TYPE": "SOĞUK KAHVELER",
            "TAX": "0",
            "UNIT": "ADED",
            "DISCOUNT": "0"
        },
        {
            "CODE": "M-00019",
            "NAME": "CLOD BREW",
            "BUYINGPRICE": "0",
            "PRICE": "15",
            "CURRENCY": "TRY",
            "TYPE": "SOĞUK KAHVELER",
            "TAX": "0",
            "UNIT": "ADED",
            "DISCOUNT": "0"
        },
        {
            "CODE": "M-00020",
            "NAME": "AFFOGATO",
            "BUYINGPRICE": "0",
            "PRICE": "12",
            "CURRENCY": "TRY",
            "TYPE": "SOĞUK KAHVELER",
            "TAX": "0",
            "UNIT": "ADED",
            "DISCOUNT": "0"
        },
        {
            "CODE": "M-00021",
            "NAME": "SHOT ESPRESSO",
            "BUYINGPRICE": "0",
            "PRICE": "23",
            "CURRENCY": "TRY",
            "TYPE": "EKSTRA",
            "TAX": "0",
            "UNIT": "ADED",
            "DISCOUNT": "0"
        },
        {
            "CODE": "M-00022",
            "NAME": "LAKTOZSUZ SÜT",
            "BUYINGPRICE": "0",
            "PRICE": "43",
            "CURRENCY": "TRY",
            "TYPE": "EKSTRA",
            "TAX": "0",
            "UNIT": "ADED",
            "DISCOUNT": "0"
        },
        {
            "CODE": "M-00023",
            "NAME": "SOYA SÜT",
            "BUYINGPRICE": "0",
            "PRICE": "54",
            "CURRENCY": "TRY",
            "TYPE": "EKSTRA",
            "TAX": "0",
            "UNIT": "ADED",
            "DISCOUNT": "0"
        },
        {
            "CODE": "M-00024",
            "NAME": "FİLTRE KAHVE",
            "BUYINGPRICE": "0",
            "PRICE": "56",
            "CURRENCY": "TRY",
            "TYPE": "DEMLEMELER",
            "TAX": "0",
            "UNIT": "ADED",
            "DISCOUNT": "0"
        },
        {
            "CODE": "M-00025",
            "NAME": "ORTA FİLTRE KAHVE",
            "BUYINGPRICE": "0",
            "PRICE": "67",
            "CURRENCY": "TRY",
            "TYPE": "DEMLEMELER",
            "TAX": "0",
            "UNIT": "ADED",
            "DISCOUNT": "0"
        },
        {
            "CODE": "M-00026",
            "NAME": "CHEMEX",
            "BUYINGPRICE": "0",
            "PRICE": "23",
            "CURRENCY": "TRY",
            "TYPE": "DEMLEMELER",
            "TAX": "0",
            "UNIT": "ADED",
            "DISCOUNT": "0"
        },
        {
            "CODE": "M-00027",
            "NAME": "V60",
            "BUYINGPRICE": "0",
            "PRICE": "12",
            "CURRENCY": "TRY",
            "TYPE": "DEMLEMELER",
            "TAX": "0",
            "UNIT": "ADED",
            "DISCOUNT": "0"
        },
        {
            "CODE": "M-00028",
            "NAME": "AEROPRESS",
            "BUYINGPRICE": "0",
            "PRICE": "1",
            "CURRENCY": "TRY",
            "TYPE": "DEMLEMELER",
            "TAX": "0",
            "UNIT": "ADED",
            "DISCOUNT": "0"
        },
        {
            "CODE": "M-00029",
            "NAME": "DELTER PRESS",
            "BUYINGPRICE": "0",
            "PRICE": "32",
            "CURRENCY": "TRY",
            "TYPE": "DEMLEMELER",
            "TAX": "0",
            "UNIT": "ADED",
            "DISCOUNT": "0"
        },
        {
            "CODE": "M-00030",
            "NAME": "TÜRK KAHVESİ",
            "BUYINGPRICE": "0",
            "PRICE": "3",
            "CURRENCY": "TRY",
            "TYPE": "DEMLEMELER",
            "TAX": "0",
            "UNIT": "ADED",
            "DISCOUNT": "0"
        },
        {
            "CODE": "M-00031",
            "NAME": "BİTKİ ÇAYI",
            "BUYINGPRICE": "0",
            "PRICE": "13",
            "CURRENCY": "TRY",
            "TYPE": "DEMLEMELER",
            "TAX": "0",
            "UNIT": "ADED",
            "DISCOUNT": "0"
        },
        {
            "CODE": "M-00032",
            "NAME": "ÇAY",
            "BUYINGPRICE": "0",
            "PRICE": "2",
            "CURRENCY": "TRY",
            "TYPE": "DEMLEMELER",
            "TAX": "0",
            "UNIT": "ADED",
            "DISCOUNT": "0"
        },
        {
            "CODE": "M-00033",
            "NAME": "SOĞUK ÇAY",
            "BUYINGPRICE": "0",
            "PRICE": "31",
            "CURRENCY": "TRY",
            "TYPE": "SOĞUK İÇECEKLER",
            "TAX": "0",
            "UNIT": "ADED",
            "DISCOUNT": "0"
        },
        {
            "CODE": "M-00034",
            "NAME": "LİMONATA",
            "BUYINGPRICE": "0",
            "PRICE": "3",
            "CURRENCY": "TRY",
            "TYPE": "SOĞUK İÇECEKLER",
            "TAX": "0",
            "UNIT": "ADED",
            "DISCOUNT": "0"
        },
        {
            "CODE": "M-00035",
            "NAME": "KAKAOLU MİLKSHAKE",
            "BUYINGPRICE": "0",
            "PRICE": "6",
            "CURRENCY": "TRY",
            "TYPE": "SOĞUK İÇECEKLER",
            "TAX": "0",
            "UNIT": "ADED",
            "DISCOUNT": "0"
        },
        {
            "CODE": "M-00036",
            "NAME": "SADE MİLKSHAKE",
            "BUYINGPRICE": "0",
            "PRICE": "21",
            "CURRENCY": "TRY",
            "TYPE": "SOĞUK İÇECEKLER",
            "TAX": "0",
            "UNIT": "ADED",
            "DISCOUNT": "0"
        },
        {
            "CODE": "M-00037",
            "NAME": "SU",
            "BUYINGPRICE": "0",
            "PRICE": "3",
            "CURRENCY": "TRY",
            "TYPE": "SOĞUK İÇECEKLER",
            "TAX": "0",
            "UNIT": "ADED",
            "DISCOUNT": "0"
        },
        {
            "CODE": "M-00038",
            "NAME": "SODA",
            "BUYINGPRICE": "0",
            "PRICE": "31",
            "CURRENCY": "TRY",
            "TYPE": "SOĞUK İÇECEKLER",
            "TAX": "0",
            "UNIT": "ADED",
            "DISCOUNT": "0"
        },
        {
            "CODE": "M-00039",
            "NAME": "SAN PELLEGRİNO",
            "BUYINGPRICE": "0",
            "PRICE": "12",
            "CURRENCY": "TRY",
            "TYPE": "SOĞUK İÇECEKLER",
            "TAX": "0",
            "UNIT": "ADED",
            "DISCOUNT": "0"
        },
        {
            "CODE": "M-00040",
            "NAME": "KOMBUCHA",
            "BUYINGPRICE": "0",
            "PRICE": "21",
            "CURRENCY": "TRY",
            "TYPE": "SOĞUK İÇECEKLER",
            "TAX": "0",
            "UNIT": "ADED",
            "DISCOUNT": "0"
        },
        {
            "CODE": "M-00041",
            "NAME": "KRUVASAN",
            "BUYINGPRICE": "0",
            "PRICE": "21",
            "CURRENCY": "TRY",
            "TYPE": "SANDVİÇLER",
            "TAX": "0",
            "UNIT": "ADED",
            "DISCOUNT": "0"
        },
        {
            "CODE": "M-00042",
            "NAME": "HARİO CAM KARAF 02",
            "BUYINGPRICE": "0",
            "PRICE": "21",
            "CURRENCY": "TRY",
            "TYPE": "EKİPMANLAR",
            "TAX": "0",
            "UNIT": "ADED",
            "DISCOUNT": "0"
        },
        {
            "CODE": "M-00043",
            "NAME": "HARİO SERAMİK DRİPPER 02",
            "BUYINGPRICE": "0",
            "PRICE": "2",
            "CURRENCY": "TRY",
            "TYPE": "EKİPMANLAR",
            "TAX": "0",
            "UNIT": "ADED",
            "DISCOUNT": "0"
        },
        {
            "CODE": "M-00044",
            "NAME": "DECANTER",
            "BUYINGPRICE": "0",
            "PRICE": "12",
            "CURRENCY": "TRY",
            "TYPE": "EKİPMANLAR",
            "TAX": "0",
            "UNIT": "ADED",
            "DISCOUNT": "0"
        },
        {
            "CODE": "M-00045",
            "NAME": "V60 HARİO FİLTRE 01",
            "BUYINGPRICE": "0",
            "PRICE": "12",
            "CURRENCY": "TRY",
            "TYPE": "EKİPMANLAR",
            "TAX": "0",
            "UNIT": "ADED",
            "DISCOUNT": "0"
        },
        {
            "CODE": "M-00046",
            "NAME": "V60 HARİO FİLTRE 02",
            "BUYINGPRICE": "0",
            "PRICE": "12",
            "CURRENCY": "TRY",
            "TYPE": "EKİPMANLAR",
            "TAX": "0",
            "UNIT": "ADED",
            "DISCOUNT": "0"
        },
        {
            "CODE": "M-00047",
            "NAME": "AEROPRESS",
            "BUYINGPRICE": "0",
            "PRICE": "1",
            "CURRENCY": "TRY",
            "TYPE": "EKİPMANLAR",
            "TAX": "0",
            "UNIT": "ADED",
            "DISCOUNT": "0"
        },
        {
            "CODE": "M-00048",
            "NAME": "TİMER",
            "BUYINGPRICE": "0",
            "PRICE": "21",
            "CURRENCY": "TRY",
            "TYPE": "EKİPMANLAR",
            "TAX": "0",
            "UNIT": "ADED",
            "DISCOUNT": "0"
        },
        {
            "CODE": "M-00049",
            "NAME": "DELTER PRESS",
            "BUYINGPRICE": "0",
            "PRICE": "8",
            "CURRENCY": "TRY",
            "TYPE": "EKİPMANLAR",
            "TAX": "0",
            "UNIT": "ADED",
            "DISCOUNT": "0"
        },
        {
            "CODE": "M-00050",
            "NAME": "TÜRK KAHVESİ CEZVESİ",
            "BUYINGPRICE": "0",
            "PRICE": "9",
            "CURRENCY": "TRY",
            "TYPE": "EKİPMANLAR",
            "TAX": "0",
            "UNIT": "ADED",
            "DISCOUNT": "0"
        },
        {
            "CODE": "M-00051",
            "NAME": "TERMOMETRE",
            "BUYINGPRICE": "0",
            "PRICE": "12",
            "CURRENCY": "TRY",
            "TYPE": "EKİPMANLAR",
            "TAX": "0",
            "UNIT": "ADED",
            "DISCOUNT": "0"
        },
        {
            "CODE": "M-00052",
            "NAME": "DECANTER METAL FİLTRELİ",
            "BUYINGPRICE": "0",
            "PRICE": "12",
            "CURRENCY": "TRY",
            "TYPE": "EKİPMANLAR",
            "TAX": "0",
            "UNIT": "ADED",
            "DISCOUNT": "0"
        },
        {
            "CODE": "M-00053",
            "NAME": "CHEMEX FİLTRE KAĞIDI 3 CUP",
            "BUYINGPRICE": "0",
            "PRICE": "4",
            "CURRENCY": "TRY",
            "TYPE": "EKİPMANLAR",
            "TAX": "0",
            "UNIT": "ADED",
            "DISCOUNT": "0"
        },
        {
            "CODE": "M-00054",
            "NAME": "CHEMEX FİLTRE KAĞIDI 6 CUP",
            "BUYINGPRICE": "0",
            "PRICE": "21",
            "CURRENCY": "TRY",
            "TYPE": "EKİPMANLAR",
            "TAX": "0",
            "UNIT": "ADED",
            "DISCOUNT": "0"
        },
        {
            "CODE": "M-00055",
            "NAME": "HARİO KETTLE 1,2 L",
            "BUYINGPRICE": "0",
            "PRICE": "21",
            "CURRENCY": "TRY",
            "TYPE": "EKİPMANLAR",
            "TAX": "0",
            "UNIT": "ADED",
            "DISCOUNT": "0"
        },
        {
            "CODE": "M-00056",
            "NAME": "MOTTA SİYAH 35 CL SÜT P",
            "BUYINGPRICE": "0",
            "PRICE": "31",
            "CURRENCY": "TRY",
            "TYPE": "EKİPMANLAR",
            "TAX": "0",
            "UNIT": "ADED",
            "DISCOUNT": "0"
        },
        {
            "CODE": "M-00057",
            "NAME": "MOTTA YEŞİL 50 CL SÜT P",
            "BUYINGPRICE": "0",
            "PRICE": "21",
            "CURRENCY": "TRY",
            "TYPE": "EKİPMANLAR",
            "TAX": "0",
            "UNIT": "ADED",
            "DISCOUNT": "0"
        },
        {
            "CODE": "M-00058",
            "NAME": "MOTTA RED 35 CL SÜT P",
            "BUYINGPRICE": "0",
            "PRICE": "21",
            "CURRENCY": "TRY",
            "TYPE": "EKİPMANLAR",
            "TAX": "0",
            "UNIT": "ADED",
            "DISCOUNT": "0"
        },
        {
            "CODE": "M-00059",
            "NAME": "GUATEMALA BUENA VİSTA 250 GR",
            "BUYINGPRICE": "0",
            "PRICE": "2",
            "CURRENCY": "TRY",
            "TYPE": "KAHVELER",
            "TAX": "0",
            "UNIT": "ADED",
            "DISCOUNT": "0"
        },
        {
            "CODE": "M-00060",
            "NAME": "GUATEMALA FEMALE GROWERS 250 GR",
            "BUYINGPRICE": "0",
            "PRICE": "12",
            "CURRENCY": "TRY",
            "TYPE": "KAHVELER",
            "TAX": "0",
            "UNIT": "ADED",
            "DISCOUNT": "0"
        },
        {
            "CODE": "M-00061",
            "NAME": "PERU ELİ ESPİNZO NATURAL 250 GR",
            "BUYINGPRICE": "0",
            "PRICE": "121",
            "CURRENCY": "TRY",
            "TYPE": "KAHVELER",
            "TAX": "0",
            "UNIT": "ADED",
            "DISCOUNT": "0"
        },
        {
            "CODE": "M-00062",
            "NAME": "PERU CHİRİNOS 250 GR",
            "BUYINGPRICE": "0",
            "PRICE": "21",
            "CURRENCY": "TRY",
            "TYPE": "KAHVELER",
            "TAX": "0",
            "UNIT": "ADED",
            "DISCOUNT": "0"
        },
        {
            "CODE": "M-00063",
            "NAME": "KOSTA RİKA LAS LAJAS HONEY 250 GR",
            "BUYINGPRICE": "0",
            "PRICE": "5",
            "CURRENCY": "TRY",
            "TYPE": "KAHVELER",
            "TAX": "0",
            "UNIT": "ADED",
            "DISCOUNT": "0"
        },
        {
            "CODE": "M-00064",
            "NAME": "GUATEMALA BUENA VİSTA 100 GR",
            "BUYINGPRICE": "0",
            "PRICE": "21",
            "CURRENCY": "TRY",
            "TYPE": "KAHVELER",
            "TAX": "0",
            "UNIT": "ADED",
            "DISCOUNT": "0"
        },
        {
            "CODE": "M-00065",
            "NAME": "GUATEMALA FEMALE GROWERS 100 GR",
            "BUYINGPRICE": "0",
            "PRICE": "21",
            "CURRENCY": "TRY",
            "TYPE": "KAHVELER",
            "TAX": "0",
            "UNIT": "ADED",
            "DISCOUNT": "0"
        },
        {
            "CODE": "M-00066",
            "NAME": "PERU ELİ ESPİNZO NATURAL 100 GR",
            "BUYINGPRICE": "0",
            "PRICE": "2",
            "CURRENCY": "TRY",
            "TYPE": "KAHVELER",
            "TAX": "0",
            "UNIT": "ADED",
            "DISCOUNT": "0"
        },
        {
            "CODE": "M-00067",
            "NAME": "PERU CHİRİNOS 100 GR",
            "BUYINGPRICE": "0",
            "PRICE": "12",
            "CURRENCY": "TRY",
            "TYPE": "KAHVELER",
            "TAX": "0",
            "UNIT": "ADED",
            "DISCOUNT": "0"
        },
        {
            "CODE": "M-00068",
            "NAME": "KOSTA RİKA LAS LAJAS HONEY 100 GR",
            "BUYINGPRICE": "0",
            "PRICE": "13",
            "CURRENCY": "TRY",
            "TYPE": "KAHVELER",
            "TAX": "0",
            "UNIT": "ADED",
            "DISCOUNT": "0"
        },
        {
            "CODE": "M-00069",
            "NAME": "PERU HUABAL TÜRK 250 GR",
            "BUYINGPRICE": "0",
            "PRICE": "21",
            "CURRENCY": "TRY",
            "TYPE": "KAHVELER",
            "TAX": "0",
            "UNIT": "ADED",
            "DISCOUNT": "0"
        },
        {
            "CODE": "M-00070",
            "NAME": "HONDURAS GUALME KAFEİNSİZ 250 GR",
            "BUYINGPRICE": "0",
            "PRICE": "21",
            "CURRENCY": "TRY",
            "TYPE": "KAHVELER",
            "TAX": "0",
            "UNIT": "ADED",
            "DISCOUNT": "0"
        },
        {
            "CODE": "M-00071",
            "NAME": "PERU HUABAL TÜRK 100 GR",
            "BUYINGPRICE": "0",
            "PRICE": "2",
            "CURRENCY": "TRY",
            "TYPE": "KAHVELER",
            "TAX": "0",
            "UNIT": "ADED",
            "DISCOUNT": "0"
        },
        {
            "CODE": "M-00072",
            "NAME": "HONDURAS GUALME KAFEİNSİZ 100 GR",
            "BUYINGPRICE": "0",
            "PRICE": "12",
            "CURRENCY": "TRY",
            "TYPE": "KAHVELER",
            "TAX": "0",
            "UNIT": "ADED",
            "DISCOUNT": "0"
        }
    ]
